internet_domain_local/__init__.py
internet_domain_local/internet_domain_local.py
internet_domain_local/internet_domain_local_constants.py
internet_domain_local-0.0.34.dist-info/METADATA
internet_domain_local-0.0.34.dist-info/WHEEL
internet_domain_local-0.0.34.dist-info/top_level.txt
internet_domain_local-0.0.34.dist-info/RECORD
