Metadata-Version: 2.4
Name: internet-domain-local
Version: 0.0.34
Summary: PyPI Package for Circles internet-domain-local Python
Home-page: https://github.com/circles-zone/internet-domain-local-python-package
Author: Circles
Author-email: info@circlez.ai
Classifier: Programming Language :: Python :: 3
Classifier: License :: Other/Proprietary License
Classifier: Operating System :: OS Independent
Requires-Dist: logger-local>=0.0.135
Requires-Dist: database-mysql-local>=0.0.290
Requires-Dist: storage-local>=0.1.41
Dynamic: author
Dynamic: author-email
Dynamic: classifier
Dynamic: description
Dynamic: description-content-type
Dynamic: home-page
Dynamic: requires-dist
Dynamic: summary
